icai_ca_scraper/__init__.py
icai_ca_scraper/scraper.py
icai_ca_scraper-0.1.0.dist-info/licenses/LICENSE
icai_ca_scraper-0.1.0.dist-info/METADATA
icai_ca_scraper-0.1.0.dist-info/WHEEL
icai_ca_scraper-0.1.0.dist-info/top_level.txt
icai_ca_scraper-0.1.0.dist-info/RECORD
