Metadata-Version: 2.4
Name: icai-ca-scraper
Version: 0.1.0
Summary: A Python package to fetch CA member details from ICAI website
Author-email: Shrey Baheti <sbshrey@gmaill.com>
License: MIT
Project-URL: Homepage, https://github.com/ShreyBaheti/icai-ca-scraper
Project-URL: Bug Tracker, https://github.com/ShreyBaheti/icai-ca-scraper/issues
Keywords: icai,ca,chartered-accountant,india,scraper,api
Classifier: Development Status :: 4 - Beta
Classifier: Intended Audience :: Developers
Classifier: Operating System :: OS Independent
Classifier: Programming Language :: Python :: 3
Classifier: Programming Language :: Python :: 3.7
Classifier: Programming Language :: Python :: 3.8
Classifier: Programming Language :: Python :: 3.9
Classifier: Programming Language :: Python :: 3.10
Classifier: Programming Language :: Python :: 3.11
Classifier: Topic :: Internet :: WWW/HTTP :: Dynamic Content
Classifier: Topic :: Software Development :: Libraries :: Python Modules
Requires-Python: >=3.7
License-File: LICENSE
Requires-Dist: requests>=2.25.0
Requires-Dist: beautifulsoup4>=4.9.0
Requires-Dist: urllib3>=1.26.0
Dynamic: license-file
